ulstools/__init__.py
ulstools/cfg.py
ulstools/env.py
ulstools/num.py
ulstools/apps/__init__.py
ulstools/apps/pdfmerger/__init__.py
ulstools/apps/pdfmerger/pdfmerger.py
ulstools/apps/pdfmerger/pdfmerger.ui
ulstools-0.10.4.dist-info/LICENSE
ulstools-0.10.4.dist-info/METADATA
ulstools-0.10.4.dist-info/WHEEL
ulstools-0.10.4.dist-info/entry_points.txt
ulstools-0.10.4.dist-info/top_level.txt
ulstools-0.10.4.dist-info/RECORD
