Metadata-Version: 2.1
Name: ulstools
Version: 0.10.4
Summary: Miscellaneous tools for ULS
Home-page: https://github.com/jjnurminen/ulstools
Author: Jussi Nurminen
Author-email: jnu@iki.fi
License: GPLv3
Platform: UNKNOWN
